LICENSE
MANIFEST.in
Makefile
README.rst
setup.py
docs/conf.py
docs/index.rst
docs/sphinxcontrib.wiki.rst
docs/wiki.rst
sphinxcontrib/__init__.py
sphinxcontrib/wiki.py
sphinxcontrib_wiki.egg-info/PKG-INFO
sphinxcontrib_wiki.egg-info/SOURCES.txt
sphinxcontrib_wiki.egg-info/dependency_links.txt
sphinxcontrib_wiki.egg-info/namespace_packages.txt
sphinxcontrib_wiki.egg-info/requires.txt
sphinxcontrib_wiki.egg-info/top_level.txt
sphinxcontrib_wiki.egg-info/zip-safe
tests/__init__.py
tests/util.py
tests/_tpl/Makefile
tests/_tpl/__init__.py
tests/_tpl/_test_tpl.py
tests/_tpl/docs/conf.py
tests/_tpl/docs/index.rst
tests/basic/Makefile
tests/basic/__init__.py
tests/basic/test_basic.py
tests/basic/docs/conf.py
tests/basic/docs/index.rst
tests/parents/Makefile
tests/parents/__init__.py
tests/parents/test_parents.py
tests/parents/docs/conf.py
tests/parents/docs/index.rst
tests/parents/docs/index.sub.rst
tests/parents/docs/index.sub.sub.sub.rst
tests/parents/docs/_build/Makefile
tests/refs/Makefile
tests/refs/__init__.py
tests/refs/test_refs.py
tests/refs/docs/conf.py
tests/refs/docs/index.rst
tests/refs/docs/modules.rst
tests/refs/docs/some_pkg.other_mod.rst
tests/refs/docs/some_pkg.rst
tests/refs/docs/some_pkg.some_mod.rst
tests/refs/docs/twice.rst
tests/refs/some_pkg/__init__.py
tests/refs/some_pkg/other_mod.py
tests/refs/some_pkg/some_mod.py
tests/titles/Makefile
tests/titles/__init__.py
tests/titles/test_titles.py
tests/titles/docs/conf.py
tests/titles/docs/index.rst