Metadata-Version: 1.1
Name: sphinxcontrib-wiki
Version: 0.5.0
Summary: Assemble sections into wiki pages in sphinx documents
Home-page: https://github.com/amirkdv/sphinxcontrib-wiki
Author: Amir Kadivar
Author-email: amir@amirkdv.ca
License: MIT
Platform: any
Classifier: Development Status :: 4 - Beta
Classifier: Environment :: Console
Classifier: Environment :: Web Environment
Classifier: Framework :: Sphinx :: Extension
Classifier: Intended Audience :: Developers
Classifier: License :: OSI Approved :: MIT License
Classifier: Operating System :: OS Independent
Classifier: Programming Language :: Python
Classifier: Programming Language :: Python :: 2.7
Classifier: Programming Language :: Python :: 3.5
Classifier: Topic :: Documentation
Classifier: Topic :: Documentation :: Sphinx
Classifier: Topic :: Utilities
